web3auth/__init__.py
web3auth/apps.py
web3auth/backend.py
web3auth/forms.py
web3auth/settings.py
web3auth/urls.py
web3auth/utils.py
web3auth/views.py
web3auth/static/web3auth/css/web3auth.css
web3auth/static/web3auth/js/web3auth.js
web3auth/templates/web3auth/base.html
web3auth/templates/web3auth/signup.html
django_web3_auth-0.1.3.dist-info/AUTHORS.rst
django_web3_auth-0.1.3.dist-info/LICENSE
django_web3_auth-0.1.3.dist-info/METADATA
django_web3_auth-0.1.3.dist-info/WHEEL
django_web3_auth-0.1.3.dist-info/top_level.txt
django_web3_auth-0.1.3.dist-info/RECORD
