Metadata-Version: 2.1
Name: django-web3-auth
Version: 0.1.3
Summary: django-web3-auth is a pluggable Django app that enables login/signup via an Ethereum wallet (a la CryptoKitties). The user authenticates themselves by digitally signing the session key with their wallet's private key.
Home-page: https://github.com/Bearle/django-web3-auth
Author: Bearle
Author-email: tech@bearle.ru
License: MIT
Keywords: django-web3-auth
Platform: UNKNOWN
Classifier: Development Status :: 3 - Alpha
Classifier: Framework :: Django :: 1.11
Classifier: Framework :: Django :: 2.0
Classifier: Intended Audience :: Developers
Classifier: License :: OSI Approved :: BSD License
Classifier: Natural Language :: English
Classifier: Programming Language :: Python :: 2
Classifier: Programming Language :: Python :: 2.7
Classifier: Programming Language :: Python :: 3
Classifier: Programming Language :: Python :: 3.4
Classifier: Programming Language :: Python :: 3.5
Classifier: Programming Language :: Python :: 3.6
Requires-Dist: ethereum (==2.3.2)
Requires-Dist: rlp (==2.0.1)
Requires-Dist: eth-utils (>=1.0.3)
Requires-Dist: Django (>=2.0)
